localtest/__init__.py
localtest/cli.py
localtest-1.0.1.dist-info/METADATA
localtest-1.0.1.dist-info/WHEEL
localtest-1.0.1.dist-info/entry_points.txt
localtest-1.0.1.dist-info/top_level.txt
localtest-1.0.1.dist-info/RECORD
