Metadata-Version: 2.4
Name: localtest
Version: 1.0.1
Summary: A home to locally running tests such as testing your network speeds!
Author: Sabio Tang
Requires-Python: >=3.8
Requires-Dist: speedtest-cli
